parallax_core/__init__.py
parallax_core/collapse.py
parallax_core/environment.py
parallax_core/evaluator.py
parallax_core/grammar.lark
parallax_core/main.py
parallax_core/nodes.py
parallax_core/parser.py
parallax_core/repl.py
parallax_core/values.py
parallax_lang-1.0.0.dist-info/METADATA
parallax_lang-1.0.0.dist-info/WHEEL
parallax_lang-1.0.0.dist-info/entry_points.txt
parallax_lang-1.0.0.dist-info/top_level.txt
parallax_lang-1.0.0.dist-info/RECORD
