Metadata-Version: 2.4
Name: parallax-lang
Version: 1.0.0
Requires-Dist: lark
Dynamic: requires-dist
